kakuyomub/__init__.py
kakuyomub/downloader.py
kakuyomub/episode.py
kakuyomub/epub_maker.py
kakuyomub/main.py
kakuyomub/template.html
kakuyomub/works.py
kakuyomub-0.2.2.dist-info/METADATA
kakuyomub-0.2.2.dist-info/WHEEL
kakuyomub-0.2.2.dist-info/top_level.txt
kakuyomub-0.2.2.dist-info/RECORD
